MANIFEST.in
setup.py
docs/HISTORY.txt
src/menhir/__init__.py
src/menhir.contenttype.document.egg-info/PKG-INFO
src/menhir.contenttype.document.egg-info/SOURCES.txt
src/menhir.contenttype.document.egg-info/dependency_links.txt
src/menhir.contenttype.document.egg-info/namespace_packages.txt
src/menhir.contenttype.document.egg-info/not-zip-safe
src/menhir.contenttype.document.egg-info/requires.txt
src/menhir.contenttype.document.egg-info/top_level.txt
src/menhir/contenttype/__init__.py
src/menhir/contenttype/document/README.txt
src/menhir/contenttype/document/__init__.py
src/menhir/contenttype/document/configure.zcml
src/menhir/contenttype/document/document.py
src/menhir/contenttype/document/ftesting.zcml
src/menhir/contenttype/document/tests.py
src/menhir/contenttype/document/document_templates/documentview.pt
src/menhir/contenttype/document/locales/en/LC_MESSAGES/menhir.contenttype.document.mo
src/menhir/contenttype/document/locales/en/LC_MESSAGES/menhir.contenttype.document.po
src/menhir/contenttype/document/locales/fr/LC_MESSAGES/menhir.contenttype.document.mo
src/menhir/contenttype/document/locales/fr/LC_MESSAGES/menhir.contenttype.document.po