Metadata-Version: 1.0
Name: menhir.contenttype.document
Version: 0.1
Summary: Dolmen contenttype extension : document
Home-page: http://gitweb.dolmen-project.org/
Author: Souheil Chelfouh
Author-email: trollfot@gmail.com
License: GPL
Download-URL: http://pypi.python.org/pypi/menhir.contenttype.document
Keywords: Grok Zope3 CMS Dolmen
Platform: Any
Classifier: License :: OSI Approved :: GNU General Public License (GPL)
Classifier: Programming Language :: Python
